whisperplus/__init__.py
whisperplus/app.py
whisperplus/test.py
whisperplus/pipelines/__init__.py
whisperplus/pipelines/autollm_chatbot.py
whisperplus/pipelines/lancedb_chatbot.py
whisperplus/pipelines/long_text_summarization.py
whisperplus/pipelines/summarization.py
whisperplus/pipelines/text2speech.py
whisperplus/pipelines/whisper.py
whisperplus/pipelines/whisper_autocaption.py
whisperplus/pipelines/whisper_diarize.py
whisperplus/utils/__init__.py
whisperplus/utils/download_utils.py
whisperplus/utils/text_utils.py
whisperplus-0.3.0.dist-info/LICENSE
whisperplus-0.3.0.dist-info/METADATA
whisperplus-0.3.0.dist-info/WHEEL
whisperplus-0.3.0.dist-info/top_level.txt
whisperplus-0.3.0.dist-info/RECORD
