Metadata-Version: 2.1
Name: whisperplus
Version: 0.3.0
Summary: WhisperPlus: A Python library for WhisperPlus API.
Home-page: https://github.com/kadirnar/whisperplus
Author: kadirnar
Author-email: kadir.nar@hotmail.com
License: Apache License 2.0
License-File: LICENSE
Requires-Dist: torch >=2.0.0
Requires-Dist: torchvision >=0.15.0
Requires-Dist: torchaudio >=2.0.0
Requires-Dist: gradio >=4.14.0
Requires-Dist: langchain >=0.1.0
Requires-Dist: moviepy >=1.0.3
Requires-Dist: numpy >=1.24.1
Requires-Dist: pyannote.audio >=3.1.0
Requires-Dist: pyannote.core >=5.0.0
Requires-Dist: pyannote.database >=5.0.1
Requires-Dist: pyannote.metrics >=3.2.1
Requires-Dist: pyannote.pipeline >=3.0.1
Requires-Dist: pytube >=15.0.0
Requires-Dist: Requests >=2.31.0
Requires-Dist: sentence-transformers
Requires-Dist: ctransformers
Requires-Dist: accelerate
Requires-Dist: pre-commit ==3.4.0
Requires-Dist: autollm >=0.1.9
Requires-Dist: speechbrain >=0.5.16
Requires-Dist: bitsandbytes
Requires-Dist: hqq
